{
    "Players": {
        "Savannah Berry": "S7",
        "GhoulishOnibi": "S6",
        "Salty_Plaguez": "S6",
        "JonesAddict": "S5",
        "Miyunori": "B4",
        "Musicialgamer": "B4",
        "Miyuki_____": "B4",
        "CheeseNmac": "B4",
        "X_Mino_X": "B4",
        "MaryWolf01": "S1",
        "Zoot": "S1",
        "Firney": "S1"
    },
    "Recipes": {

    },
    "DrinkSkins": [ 0 ],
    "CustomJoinMessage": "",
    "Playlist1Name": "",
    "Playlist2Name": "",
    "Playlist3Name": "",
    "DefaultBarLayout": 0,
    "ColorPicker": true,
    "VerifyOnStart": true,
    "AllowDVCStaff": true,
    "UseDVC18Plus": false,
    "UseDVC21Plus": false,
    "ReplaceGroupBanners": false,
    "ReplacePhotoBanners": false,
    "IsActive": true
}