{
    "Players": {
        "Only Mirage": "S7",

        "THEBOXMAN": "B2",

        "Ｅｘａｍｐｌｅ": "D2",
        "jezyjule21": "D2",

        "NylaB0nes": "D3",

        "_Plasma": "S1",
        "ƒALL€₪₭¡₪g₽A₪₫A": "S1",
        "Fe Psyt": "S1",
        "BIF_Teapot": "S1",
        "D̸e҉m̶̍̄o̶几's": "S1",
        "Julia Ortiz": "S1",
        "Stinky Gwew": "S1",

        "AerrahTessa": "V2"
    },
    "Recipes": {

    },
    "DrinkSkins": [ 0 ],
    "TeamColor": "FFFFFF",
    "CustomJoinMessage": "",
    "Playlist1Name": "2000's Throwback Vibes",
    "Playlist2Name": "2000's R&B Party Mix",
    "Playlist3Name": "Late Night Drives With The Boys",
    "DefaultBarLayout": 0,
    "ColorPicker": false,
    "VerifyOnStart": false,
    "AllowDVCStaff": true,
    "UseDVC18Plus": false,
    "UseDVC21Plus": false,
    "ReplaceGroupBanners": false,
    "ReplacePhotoBanners": false
}